diwork/__init__.py
diwork/__main__.py
diwork/__version__.py
diwork/main.py
diwork/diwork_mains/__init__.py
diwork/diwork_mains/diwork_archive.py
diwork/diwork_mains/diwork_clone.py
diwork/diwork_mains/diwork_contains.py
diwork/diwork_mains/diwork_diff.py
diwork/diwork_mains/diwork_diffclone.py
diwork/diwork_mains/diwork_difx.py
diwork/diwork_mains/diwork_exec.py
diwork/diwork_mains/diwork_hash.py
diwork/diwork_mains/diwork_help.py
diwork/diwork_mains/diwork_repeats.py
diwork/diwork_mains/diwork_sshclone.py
diwork/diwork_ways/__init__.py
diwork/diwork_ways/diwork_parse.py
diwork/diwork_ways/diwork_sup.py
diwork-1.4.1.dist-info/LICENSE
diwork-1.4.1.dist-info/METADATA
diwork-1.4.1.dist-info/WHEEL
diwork-1.4.1.dist-info/entry_points.txt
diwork-1.4.1.dist-info/top_level.txt
diwork-1.4.1.dist-info/RECORD
