Metadata-Version: 2.1
Name: diwork
Version: 1.4.1
License-File: LICENSE
Requires-Dist: argparse
Requires-Dist: tqdm
